pysecs/__init__.py
pysecs/secs.py
pysecs-0.3.0.dist-info/LICENSE
pysecs-0.3.0.dist-info/METADATA
pysecs-0.3.0.dist-info/WHEEL
pysecs-0.3.0.dist-info/top_level.txt
pysecs-0.3.0.dist-info/RECORD
