Metadata-Version: 2.1
Name: pysecs
Version: 0.3.0
Summary: Spherical Elementary Current System (SECS) Calculations.
Author-email: Greg Lucas <greg.m.lucas@gmail.com>
License: Copyright (c) 2018 Greg Lucas
Project-URL: homepage, https://greglucas.github.io/pysecs/
Project-URL: repository, https://github.com/greglucas/pysecs
Keywords: Spherical Elementary Current Systems,SECS,Ionosphere,Atmosphere,Geomagnetic
Classifier: Development Status :: 4 - Beta
Classifier: Intended Audience :: Developers
Classifier: License :: OSI Approved :: MIT License
Classifier: Natural Language :: English
Classifier: Programming Language :: Python :: 3
Classifier: Programming Language :: Python :: 3.10
Classifier: Programming Language :: Python :: 3.11
Classifier: Programming Language :: Python :: 3.12
Classifier: Programming Language :: Python :: 3.13
Classifier: Topic :: Software Development
Classifier: Topic :: Scientific/Engineering
Classifier: Operating System :: Microsoft :: Windows
Classifier: Operating System :: POSIX
Classifier: Operating System :: Unix
Classifier: Operating System :: MacOS
Requires-Python: >=3.10
License-File: LICENSE
Requires-Dist: numpy>=1.23
Provides-Extra: test
Requires-Dist: pytest; extra == "test"
Requires-Dist: pytest-cov; extra == "test"
Provides-Extra: doc
Requires-Dist: matplotlib; extra == "doc"
Requires-Dist: sphinx; extra == "doc"
Requires-Dist: sphinx_gallery; extra == "doc"
Requires-Dist: pydata-sphinx-theme; extra == "doc"
Provides-Extra: dev
Requires-Dist: pysecs[doc,test]; extra == "dev"
Requires-Dist: mypy; extra == "dev"
Requires-Dist: pre-commit; extra == "dev"
Requires-Dist: ruff; extra == "dev"
